Metadata-Version: 2.1
Name: oneNeuron-pypi-isaiyamudhugit
Version: 0.0.3
Summary: Its a implementation of perceptron
Home-page: https://github.com/isaiyamudhugit/oneNeuron_pypi
Author: isaiyamudhugit
Author-email: isaiyamudhu@yahoo.co.in
License: UNKNOWN
Project-URL: Bug Tracker, https://github.com/isaiyamudhugit/oneNeuron_pypi/issues
Platform: UNKNOWN
Classifier: Programming Language :: Python :: 3
Classifier: License :: OSI Approved :: MIT License
Classifier: Operating System :: OS Independent
Requires-Python: >=3.7
License-File: LICENSE
Requires-Dist: numpy
Requires-Dist: tqdm
